Product_Tag_generator/Tags.py
Product_Tag_generator/__init__.py
Product_Tag_generator-0.0.1.dist-info/LICENSE
Product_Tag_generator-0.0.1.dist-info/METADATA
Product_Tag_generator-0.0.1.dist-info/WHEEL
Product_Tag_generator-0.0.1.dist-info/top_level.txt
Product_Tag_generator-0.0.1.dist-info/RECORD
