Metadata-Version: 2.2
Name: Product_Tag_generator
Version: 0.0.1
Summary: A simple library to extract tags from product titles
Author: Akash Venkatesan
Author-email: akashv1006@gmail.com
License: MIT
Requires-Python: >=3.7
License-File: LICENSE
Dynamic: author
Dynamic: author-email
Dynamic: description
Dynamic: description-content-type
Dynamic: license
Dynamic: requires-python
Dynamic: summary
